[
    {
        "track_name":"Thank God It's Christmas",
        "artist_name":"Queen",
        "played_at":1760817058559
    },
    {
        "track_name":"Thank God It's Christmas",
        "artist_name":"Queen",
        "played_at":1760817058559
    },
    {
        "track_name":"Last Christmas",
        "artist_name":"Ariana Grande",
        "played_at":1760818204763
    },
    {
        "track_name":"Last Christmas",
        "artist_name":"Ariana Grande",
        "played_at":1760818204763
    },
    {
        "track_name":"What Christmas Means to Me (feat. Stevie Wonder)",
        "artist_name":"John Legend",
        "played_at":1760818365713
    },
    {
        "track_name":"What Christmas Means to Me (feat. Stevie Wonder)",
        "artist_name":"John Legend",
        "played_at":1760818365713
    },
    {
        "track_name":"Last Christmas",
        "artist_name":"Wham!",
        "played_at":1760818629609
    },
    {
        "track_name":"Last Christmas",
        "artist_name":"Wham!",
        "played_at":1760818629609
    },
    {
        "track_name":"Frosty The Snowman",
        "artist_name":"Ella Fitzgerald",
        "played_at":1760818761305
    },
    {
        "track_name":"Frosty The Snowman",
        "artist_name":"Ella Fitzgerald",
        "played_at":1760818761305
    },
    {
        "track_name":"My Only Wish (This Year)",
        "artist_name":"Britney Spears",
        "played_at":1760819023806
    },
    {
        "track_name":"My Only Wish (This Year)",
        "artist_name":"Britney Spears",
        "played_at":1760819023806
    },
    {
        "track_name":"Where Are You Christmas?",
        "artist_name":"The Pretty Reckless",
        "played_at":1760819212956
    },
    {
        "track_name":"Where Are You Christmas?",
        "artist_name":"The Pretty Reckless",
        "played_at":1760819212956
    },
    {
        "track_name":"The Prayer",
        "artist_name":"C\u00e9line Dion",
        "played_at":1760819489148
    },
    {
        "track_name":"The Prayer",
        "artist_name":"C\u00e9line Dion",
        "played_at":1760819489148
    },
    {
        "track_name":"Santa Baby (with Henri Ren\u00e9 & His Orchestra)",
        "artist_name":"Eartha Kitt",
        "played_at":1760819695138
    },
    {
        "track_name":"Santa Baby (with Henri Ren\u00e9 & His Orchestra)",
        "artist_name":"Eartha Kitt",
        "played_at":1760819695138
    },
    {
        "track_name":"I Saw Mommy Kissing Santa Claus",
        "artist_name":"The Jackson 5",
        "played_at":1760819876281
    },
    {
        "track_name":"I Saw Mommy Kissing Santa Claus",
        "artist_name":"The Jackson 5",
        "played_at":1760819876281
    },
    {
        "track_name":"Mary, Did You Know?",
        "artist_name":"Pentatonix",
        "played_at":1760820081023
    },
    {
        "track_name":"Mary, Did You Know?",
        "artist_name":"Pentatonix",
        "played_at":1760820081023
    },
    {
        "track_name":"Blue Christmas",
        "artist_name":"Elvis Presley",
        "played_at":1760820211297
    },
    {
        "track_name":"Blue Christmas",
        "artist_name":"Elvis Presley",
        "played_at":1760820211297
    },
    {
        "track_name":"Winter Wonderland - Remastered 2006",
        "artist_name":"Bing Crosby",
        "played_at":1760820362670
    },
    {
        "track_name":"Winter Wonderland - Remastered 2006",
        "artist_name":"Bing Crosby",
        "played_at":1760820362670
    },
    {
        "track_name":"Santa, Can\u2019t You Hear Me",
        "artist_name":"Kelly Clarkson",
        "played_at":1760820618255
    },
    {
        "track_name":"Santa, Can\u2019t You Hear Me",
        "artist_name":"Kelly Clarkson",
        "played_at":1760820618255
    },
    {
        "track_name":"White Christmas - 1947 Version",
        "artist_name":"Bing Crosby",
        "played_at":1760820810614
    },
    {
        "track_name":"White Christmas - 1947 Version",
        "artist_name":"Bing Crosby",
        "played_at":1760820810614
    },
    {
        "track_name":"Run Rudolph Run",
        "artist_name":"Chuck Berry",
        "played_at":1760820950858
    },
    {
        "track_name":"Run Rudolph Run",
        "artist_name":"Chuck Berry",
        "played_at":1760820950858
    },
    {
        "track_name":"Merry Christmas, Happy Holidays",
        "artist_name":"*NSYNC",
        "played_at":1760821206386
    },
    {
        "track_name":"Merry Christmas, Happy Holidays",
        "artist_name":"*NSYNC",
        "played_at":1760821206386
    },
    {
        "track_name":"Lonely This Christmas",
        "artist_name":"Mud",
        "played_at":1760821420658
    },
    {
        "track_name":"Lonely This Christmas",
        "artist_name":"Mud",
        "played_at":1760821420658
    },
    {
        "track_name":"Like It's Christmas",
        "artist_name":"Jonas Brothers",
        "played_at":1760821621520
    },
    {
        "track_name":"Like It's Christmas",
        "artist_name":"Jonas Brothers",
        "played_at":1760821621520
    },
    {
        "track_name":"Christmas Tree Farm",
        "artist_name":"Taylor Swift",
        "played_at":1760821849654
    },
    {
        "track_name":"Christmas Tree Farm",
        "artist_name":"Taylor Swift",
        "played_at":1760821849654
    },
    {
        "track_name":"O Holy Night - Spotify Singles Holiday",
        "artist_name":"Ravyn Lenae",
        "played_at":1760822030937
    },
    {
        "track_name":"O Holy Night - Spotify Singles Holiday",
        "artist_name":"Ravyn Lenae",
        "played_at":1760822030937
    },
    {
        "track_name":"Christmas (Baby Please Come Home)",
        "artist_name":"Mariah Carey",
        "played_at":1760822185324
    },
    {
        "track_name":"Christmas (Baby Please Come Home)",
        "artist_name":"Mariah Carey",
        "played_at":1760822185324
    },
    {
        "track_name":"Feliz Navidad",
        "artist_name":"Jos\u00e9 Feliciano",
        "played_at":1760822367324
    },
    {
        "track_name":"Feliz Navidad",
        "artist_name":"Jos\u00e9 Feliciano",
        "played_at":1760822367324
    },
    {
        "track_name":"Here Comes Santa Claus (Right Down Santa Claus Lane)",
        "artist_name":"Elvis Presley",
        "played_at":1760822484217
    },
    {
        "track_name":"Here Comes Santa Claus (Right Down Santa Claus Lane)",
        "artist_name":"Elvis Presley",
        "played_at":1760822484217
    },
    {
        "track_name":"Sienna",
        "artist_name":"The Mar\u00edas",
        "played_at":1760834659716
    },
    {
        "track_name":"Sienna",
        "artist_name":"The Mar\u00edas",
        "played_at":1760834659716
    },
    {
        "track_name":"Manchild",
        "artist_name":"Sabrina Carpenter",
        "played_at":1760834872598
    },
    {
        "track_name":"Manchild",
        "artist_name":"Sabrina Carpenter",
        "played_at":1760834872598
    },
    {
        "track_name":"That\u2019s So True",
        "artist_name":"Gracie Abrams",
        "played_at":1760835040853
    },
    {
        "track_name":"That\u2019s So True",
        "artist_name":"Gracie Abrams",
        "played_at":1760835040853
    },
    {
        "track_name":"NOW OR NEVER",
        "artist_name":"Tkandz",
        "played_at":1760835163296
    },
    {
        "track_name":"NOW OR NEVER",
        "artist_name":"Tkandz",
        "played_at":1760835163296
    },
    {
        "track_name":"When Did You Get Hot?",
        "artist_name":"Sabrina Carpenter",
        "played_at":1760835310032
    },
    {
        "track_name":"When Did You Get Hot?",
        "artist_name":"Sabrina Carpenter",
        "played_at":1760835310032
    },
    {
        "track_name":"Just Keep Watching (From F1\u00ae The Movie)",
        "artist_name":"Tate McRae",
        "played_at":1760835452633
    },
    {
        "track_name":"Just Keep Watching (From F1\u00ae The Movie)",
        "artist_name":"Tate McRae",
        "played_at":1760835452633
    },
    {
        "track_name":"What I Want (feat. Tate McRae)",
        "artist_name":"Morgan Wallen",
        "played_at":1760835637449
    },
    {
        "track_name":"What I Want (feat. Tate McRae)",
        "artist_name":"Morgan Wallen",
        "played_at":1760835637449
    },
    {
        "track_name":"TU VAS SIN (fav)",
        "artist_name":"Rels B",
        "played_at":1760856769476
    },
    {
        "track_name":"TU VAS SIN (fav)",
        "artist_name":"Rels B",
        "played_at":1760856769476
    },
    {
        "track_name":"Eternity",
        "artist_name":"Alex Warren",
        "played_at":1760856769586
    },
    {
        "track_name":"Eternity",
        "artist_name":"Alex Warren",
        "played_at":1760856769586
    },
    {
        "track_name":"WHERE IS MY HUSBAND!",
        "artist_name":"RAYE",
        "played_at":1760856769604
    },
    {
        "track_name":"WHERE IS MY HUSBAND!",
        "artist_name":"RAYE",
        "played_at":1760856769604
    },
    {
        "track_name":"luther (with sza)",
        "artist_name":"Kendrick Lamar",
        "played_at":1760856769626
    },
    {
        "track_name":"luther (with sza)",
        "artist_name":"Kendrick Lamar",
        "played_at":1760856769626
    },
    {
        "track_name":"EYES CLOSED (with ZAYN)",
        "artist_name":"JISOO",
        "played_at":1760856769633
    },
    {
        "track_name":"EYES CLOSED (with ZAYN)",
        "artist_name":"JISOO",
        "played_at":1760856769633
    },
    {
        "track_name":"So Easy (To Fall In Love)",
        "artist_name":"Olivia Dean",
        "played_at":1760856769673
    },
    {
        "track_name":"So Easy (To Fall In Love)",
        "artist_name":"Olivia Dean",
        "played_at":1760856769673
    },
    {
        "track_name":"Sugar On My Tongue",
        "artist_name":"Tyler, The Creator",
        "played_at":1760856769703
    },
    {
        "track_name":"Sugar On My Tongue",
        "artist_name":"Tyler, The Creator",
        "played_at":1760856769703
    },
    {
        "track_name":"Manchild",
        "artist_name":"Sabrina Carpenter",
        "played_at":1760856769863
    },
    {
        "track_name":"Manchild",
        "artist_name":"Sabrina Carpenter",
        "played_at":1760856769863
    },
    {
        "track_name":"Pink Pony Club",
        "artist_name":"Chappell Roan",
        "played_at":1760856769988
    },
    {
        "track_name":"Pink Pony Club",
        "artist_name":"Chappell Roan",
        "played_at":1760856769988
    },
    {
        "track_name":"Sienna",
        "artist_name":"The Mar\u00edas",
        "played_at":1760856770168
    },
    {
        "track_name":"Sienna",
        "artist_name":"The Mar\u00edas",
        "played_at":1760856770168
    },
    {
        "track_name":"The Fate of Ophelia",
        "artist_name":"Taylor Swift",
        "played_at":1760856770256
    },
    {
        "track_name":"The Fate of Ophelia",
        "artist_name":"Taylor Swift",
        "played_at":1760856770256
    },
    {
        "track_name":"That\u2019s So True",
        "artist_name":"Gracie Abrams",
        "played_at":1760856846425
    },
    {
        "track_name":"That\u2019s So True",
        "artist_name":"Gracie Abrams",
        "played_at":1760856846425
    },
    {
        "track_name":"NOW OR NEVER",
        "artist_name":"Tkandz",
        "played_at":1760856970531
    },
    {
        "track_name":"NOW OR NEVER",
        "artist_name":"Tkandz",
        "played_at":1760856970531
    },
    {
        "track_name":"When Did You Get Hot?",
        "artist_name":"Sabrina Carpenter",
        "played_at":1760857116308
    },
    {
        "track_name":"When Did You Get Hot?",
        "artist_name":"Sabrina Carpenter",
        "played_at":1760857116308
    },
    {
        "track_name":"Just Keep Watching (From F1\u00ae The Movie)",
        "artist_name":"Tate McRae",
        "played_at":1760857259790
    },
    {
        "track_name":"Just Keep Watching (From F1\u00ae The Movie)",
        "artist_name":"Tate McRae",
        "played_at":1760857259790
    },
    {
        "track_name":"What I Want (feat. Tate McRae)",
        "artist_name":"Morgan Wallen",
        "played_at":1760857444635
    },
    {
        "track_name":"What I Want (feat. Tate McRae)",
        "artist_name":"Morgan Wallen",
        "played_at":1760857444635
    },
    {
        "track_name":"luther (with sza)",
        "artist_name":"Kendrick Lamar",
        "played_at":1760857622453
    },
    {
        "track_name":"luther (with sza)",
        "artist_name":"Kendrick Lamar",
        "played_at":1760857622453
    },
    {
        "track_name":"Eternity",
        "artist_name":"Alex Warren",
        "played_at":1760857812584
    },
    {
        "track_name":"Eternity",
        "artist_name":"Alex Warren",
        "played_at":1760857812584
    },
    {
        "track_name":"Sugar On My Tongue",
        "artist_name":"Tyler, The Creator",
        "played_at":1760857966458
    },
    {
        "track_name":"Sugar On My Tongue",
        "artist_name":"Tyler, The Creator",
        "played_at":1760857966458
    }
]